LICENSE
MANIFEST.in
README.md
setup.py
bootstrapnavtags/__init__.py
bootstrapnavtags/models.py
bootstrapnavtags/views.py
bootstrapnavtags/templatetags/__init__.py
bootstrapnavtags/templatetags/bootstrapnavtags.py
bootstrapnavtags/tests/__init__.py
bootstrapnavtags/tests/runtests.py
django_bootstrap_navtags.egg-info/PKG-INFO
django_bootstrap_navtags.egg-info/SOURCES.txt
django_bootstrap_navtags.egg-info/dependency_links.txt
django_bootstrap_navtags.egg-info/requires.txt
django_bootstrap_navtags.egg-info/top_level.txt