Metadata-Version: 1.0
Name: django-bootstrap-navtags
Version: 0.1.0
Summary: Navigation templatetags for django with twitter bootstrap.
Home-page: https://github.com/noxan/django-bootstrap-navtags
Author: Richard Stromer
Author-email: noxan@byteweaver.org
License: MIT License
Platform: UNKNOWN
